agent_skill/__init__.py
agent_skill/agents.py
agent_skill/api.py
agent_skill/cli.py
agent_skill/config.py
agent_skill/display.py
agent_skill/mcp_server.py
agent_skill/models.py
agent_skill-1.0.3.dist-info/METADATA
agent_skill-1.0.3.dist-info/WHEEL
agent_skill-1.0.3.dist-info/entry_points.txt
agent_skill-1.0.3.dist-info/licenses/LICENSE
agent_skill-1.0.3.dist-info/RECORD
