Metadata-Version: 2.4
Name: agent-skill
Version: 1.0.3
Summary: TUI and MCP Server for managing AI agent skills from SkillMaster
Project-URL: Homepage, https://skillmaster.cc/cli
Project-URL: Repository, https://github.com/davidyangcool/agent-skill
Project-URL: Documentation, https://skillmaster.cc/cli
Project-URL: Issues, https://github.com/davidyangcool/agent-skill/issues
Author-email: David Yang <david@skillmaster.cc>
Maintainer-email: SkillMaster Team <team@skillmaster.cc>
License-Expression: MIT
License-File: LICENSE
Keywords: agent,ai,claude,cli,llm,mcp,mcp-server,skill,skillmaster
Classifier: Development Status :: 5 - Production/Stable
Classifier: Environment :: Console
Classifier: Intended Audience :: Developers
Classifier: License :: OSI Approved :: MIT License
Classifier: Operating System :: OS Independent
Classifier: Programming Language :: Python :: 3
Classifier: Programming Language :: Python :: 3.9
Classifier: Programming Language :: Python :: 3.10
Classifier: Programming Language :: Python :: 3.11
Classifier: Programming Language :: Python :: 3.12
Classifier: Programming Language :: Python :: 3.13
Classifier: Topic :: Scientific/Engineering :: Artificial Intelligence
Classifier: Topic :: Software Development :: Libraries
Requires-Python: >=3.9
Requires-Dist: click>=8.0
Requires-Dist: httpx>=0.24
Requires-Dist: mcp[cli]>=1.0
Requires-Dist: rich>=13.0
Provides-Extra: dev
Requires-Dist: pytest-httpx>=0.21; extra == 'dev'
Requires-Dist: pytest>=7.0; extra == 'dev'
